LICENSE
MANIFEST.in
README.rst
raid_guard.ini
setup.py
raid_guard/__init__.py
raid_guard/kernel.py
raid_guard/kernel.pyc
raid_guard.egg-info/PKG-INFO
raid_guard.egg-info/SOURCES.txt
raid_guard.egg-info/dependency_links.txt
raid_guard.egg-info/entry_points.txt
raid_guard.egg-info/requires.txt
raid_guard.egg-info/top_level.txt