Metadata-Version: 1.1
Name: raid-guard
Version: 0.1.3
Summary: raid hard disc monitoring daemon for linux servers
Home-page: http://www.sources.e-blue.eu/
Author: Andreas Fritz
Author-email: raid_guard@bitzeit.eu
License: UNKNOWN
Download-URL: https://pypi.python.org/pypi
Keywords: raid hard-disk server monitoring daemon
Platform: UNKNOWN
Classifier: Development Status :: 3 - Alpha
Classifier: License :: OSI Approved :: MIT License
Classifier: Operating System :: Unix
Classifier: Programming Language :: Python :: 2.7
Classifier: Environment :: Console
Classifier: Natural Language :: English
Classifier: Intended Audience :: System Administrators
Classifier: Topic :: System :: Networking :: Monitoring
Classifier: Topic :: System :: Networking :: Monitoring :: Hardware Watchdog
Classifier: Topic :: System :: Systems Administration
